pyutilities/__init__.py
pyutilities/defaults.py
pyutilities/exception.py
pyutilities/logging.py
pyutilities/commands/__init__.py
pyutilities/commands/pygit.py
pyutilities/commands/pymaven.py
pyutilities/config/__init__.py
pyutilities/config/configuration.py
pyutilities/io/__init__.py
pyutilities/io/fedit.py
pyutilities/io/io_utils.py
pyutilities/network/__init__.py
pyutilities/network/pyftp.py
pyutilities/network/pyssh.py
pyutilities/utils/__init__.py
pyutilities/utils/common_utils.py
pyutilities/utils/string_utils.py
pyutilities/web/__init__.py
pyutilities/web/web_client.py
pyutilities-1.0.1.dist-info/LICENSE
pyutilities-1.0.1.dist-info/METADATA
pyutilities-1.0.1.dist-info/WHEEL
pyutilities-1.0.1.dist-info/entry_points.txt
pyutilities-1.0.1.dist-info/top_level.txt
pyutilities-1.0.1.dist-info/RECORD
