Metadata-Version: 2.1
Name: pyutilities
Version: 1.0.1
Summary: PyUtilities :: Useful python 3.x utilities library.
Home-page: https://pypi.org/project/pyutilities
Author: Dmitrii Gusev
Author-email: dmitry.ed.gusev@gmail.com
License: MIT
Project-URL: Source Code, https://github.com/dmitry-ed-gusev/pyutilities
Project-URL: Bug Tracker, https://github.com/dmitry-ed-gusev/pyutilities/issues
Keywords: python,toolset,utilities,library
Classifier: Programming Language :: Python :: 3
Classifier: Programming Language :: Python :: 3.10
Classifier: License :: OSI Approved :: MIT License
Classifier: Operating System :: OS Independent
Classifier: Development Status :: 4 - Beta
Classifier: Intended Audience :: Developers
Classifier: Topic :: Utilities
Requires-Python: >=3.10
License-File: LICENSE
Requires-Dist: xlrd
Requires-Dist: xlwt
Requires-Dist: xlwings
Requires-Dist: pyyaml
Requires-Dist: openpyxl
Requires-Dist: urllib3
Requires-Dist: paramiko
Requires-Dist: requests
Requires-Dist: prettytable
Requires-Dist: fake-useragent
